[{"id": "ectoplasm_fishing", "name": "ectoplasm fishing", "category": "normal", "noDropChance": 0, "tableRows": [{"rowItemID": "ectoplasm_fish", "name": "Ectoplasm fish", "icon": "assets/icons/items/materials/ecto_fish.png", "isMoney": false, "linearWeightScaling": true, "rowWeight": 10, "rowMinimumAmount": 1, "rowMaximumAmount": 1, "minWeightScale": 0.05, "requirementsBonuses": [{"relatedSkill": "fishing", "levelRequirement": 30, "levelMinScaling": 30, "levelMaxScaling": 50, "scalingWeight": 1, "xpBonus": 6}]}], "subTables": []}, {"id": "fishing_activity_chest", "name": "fishing activity chest", "category": "normal", "noDropChance": 0.996, "tableRows": [{"rowItemID": "fishing_chest", "name": "Fishing chest", "icon": "assets/icons/items/openables/chests/fishing_chest.png", "isMoney": false, "linearWeightScaling": true, "rowWeight": 10, "rowMinimumAmount": 1, "rowMaximumAmount": 1, "minWeightScale": 0.05, "requirementsBonuses": []}], "subTables": []}]