{"id": "sea_fishing_spear", "name": "Sea fishing (Spear)", "keywords": ["fishing"], "relatedSkillsList": ["fishing"], "requiredKeywords": [{"id": "fishing_spear", "keyword": "fishingSpear"}], "xpRewardsMap": {"fishing": 82}, "workRequired": 125, "maxWorkEfficiency": 1.9, "requirements": [{"type": "distinctKeywordItemsEquipped", "name": null, "opposite": false, "requirement": {"quantity": 3, "keywords": ["diving_gear"]}}, {"type": "skillLevel", "name": "", "opposite": false, "requirement": {"level": 30, "skill": "fishing"}}, {"type": "keywordEquipped", "name": "", "opposite": false, "requirement": {"keyword": "fishing_spear"}}], "tables": [{"isPrimary": true, "type": [], "rollAmount": 1, "tables": ["sea_fishing_spear", "shells_10_percent"]}, {"isPrimary": false, "type": ["chestTable"], "rollAmount": 1, "tables": ["fishing_activity_chest", "coral_chest_drop"]}], "rewards": [], "icon": "assets/icons/activities/spear_fishing_sea.png"}